hdtopology-0.0.2.data/purelib/hdtopology/__init__.py
hdtopology-0.0.2.data/purelib/hdtopology/_hdtopology.so
hdtopology-0.0.2.data/purelib/hdtopology/hdtopology.py
hdtopology-0.0.2.dist-info/LICENSE
hdtopology-0.0.2.dist-info/METADATA
hdtopology-0.0.2.dist-info/WHEEL
hdtopology-0.0.2.dist-info/top_level.txt
hdtopology-0.0.2.dist-info/RECORD
