Metadata-Version: 2.1
Name: hdtopology
Version: 0.0.2
Summary: Topological Data Analysis Library for NDDAV System
Home-page: https://github.com/LLNL/hdtopology
Author: Shusen Liu, Peer-Timo Bremer
Author-email: liu42@llnl.gov, bremer5@llnl.gov
License: BSD-3
Keywords: Topological Data Analysis,High-Dimensional Data
Platform: UNKNOWN
Classifier: Programming Language :: Python :: 3
Classifier: Programming Language :: C++
Classifier: License :: OSI Approved :: BSD License
Requires-Dist: numpy (>=1.19.0)
Requires-Dist: hdff
Requires-Dist: ngl
